relations_restx/__init__.py
relations_restx/api.py
relations_restx/resource.py
relations_restx-0.6.2.dist-info/LICENSE.txt
relations_restx-0.6.2.dist-info/METADATA
relations_restx-0.6.2.dist-info/WHEEL
relations_restx-0.6.2.dist-info/top_level.txt
relations_restx-0.6.2.dist-info/RECORD
