Metadata-Version: 2.1
Name: relations-restx
Version: 0.6.2
Summary: CRUD API from DB Modeling using the Flask-RESTX library
Home-page: https://github.com/relations-dil/python-relations-restx
Author: Gaffer Fitch
Author-email: relations@gaf3.com
Classifier: Programming Language :: Python :: 3
Classifier: License :: OSI Approved :: MIT License
License-File: LICENSE.txt
Requires-Dist: Werkzeug (==2.1.2)
Requires-Dist: flask (==2.1.2)
Requires-Dist: flask-restx (==0.5.1)
Requires-Dist: opengui (==0.8.8)
Requires-Dist: relations-dil (==0.6.12)
